LICENSE
MANIFEST.in
README.rst
setup.py
pygments_style_github/__init__.py
pygments_style_github.egg-info/PKG-INFO
pygments_style_github.egg-info/SOURCES.txt
pygments_style_github.egg-info/dependency_links.txt
pygments_style_github.egg-info/entry_points.txt
pygments_style_github.egg-info/requires.txt
pygments_style_github.egg-info/top_level.txt