Metadata-Version: 1.0
Name: pygments-style-github
Version: 0.4
Summary: Pygments version of the github theme.
Home-page: https://github.com/hugomaiavieira/pygments-style-github
Author: Hugo Maia Vieira
Author-email: hugomaiavieira@gmail.com
License: BSD
Keywords: pygments style github
Platform: UNKNOWN
Classifier: Development Status :: 4 - Beta
Classifier: Environment :: Plugins
Classifier: Intended Audience :: Developers
Classifier: License :: OSI Approved :: BSD License
Classifier: Operating System :: OS Independent
Classifier: Programming Language :: Python
Classifier: Programming Language :: Python :: 2
Classifier: Programming Language :: Python :: 3
Classifier: Topic :: Software Development :: Libraries :: Python Modules
